void/__init__.py
void-0.1.3.dist-info/LICENSE
void-0.1.3.dist-info/METADATA
void-0.1.3.dist-info/WHEEL
void-0.1.3.dist-info/top_level.txt
void-0.1.3.dist-info/RECORD
