Metadata-Version: 2.1
Name: void
Version: 0.1.3
Summary: Void object in Python
Home-page: https://github.com/drozdowsky/void/
Author: drozdowsky
Author-email: hdrozdow+github@pm.me
License: MIT
Platform: UNKNOWN
Requires-Dist: six
